<?xml version="1.0" encoding="UTF-8"?>
<!DOCTYPE mapper PUBLIC "-//mybatis.org//DTD Mapper 3.0//EN" "http://mybatis.org/dtd/mybatis-3-mapper.dtd">
<mapper namespace="com.test.mapper.DsmsTrainersMapper">
  <resultMap id="BaseResultMap" type="com.test.bean.DsmsTrainers">
    <!--
      WARNING - @mbg.generated
      This element is automatically generated by MyBatis Generator, do not modify.
      This element was generated on Thu May 23 23:24:09 CST 2019.
    -->
    <id column="ID" jdbcType="DECIMAL" property="id" />
    <result column="TRAINER_NO" jdbcType="VARCHAR" property="trainerNo" />
    <result column="PASSWORD" jdbcType="VARCHAR" property="password" />
    <result column="NAME" jdbcType="VARCHAR" property="name" />
    <result column="GENDER" jdbcType="CHAR" property="gender" />
    <result column="AGE" jdbcType="DECIMAL" property="age" />
    <result column="DRIVING_YEARS" jdbcType="DECIMAL" property="drivingYears" />
    <result column="PHONE" jdbcType="DECIMAL" property="phone" />
    <result column="ID_NUMBER" jdbcType="VARCHAR" property="idNumber" />
    <result column="LICENSE_TYPE" jdbcType="VARCHAR" property="licenseType" />
    <result column="LICENSE_NO" jdbcType="VARCHAR" property="licenseNo" />
    <result column="CAR_ID" jdbcType="DECIMAL" property="carId" />
    <result column="SALARY" jdbcType="DECIMAL" property="salary" />
    <result column="JOIN_DATE" jdbcType="DATE" property="joinDate" />
    <result column="FLAG" jdbcType="VARCHAR" property="flag" />
    <result column="COMMENTS" jdbcType="VARCHAR" property="comments" />
  </resultMap>
  <sql id="Example_Where_Clause">
    <!--
      WARNING - @mbg.generated
      This element is automatically generated by MyBatis Generator, do not modify.
      This element was generated on Thu May 23 23:24:09 CST 2019.
    -->
    <where>
      <foreach collection="oredCriteria" item="criteria" separator="or">
        <if test="criteria.valid">
          <trim prefix="(" prefixOverrides="and" suffix=")">
            <foreach collection="criteria.criteria" item="criterion">
              <choose>
                <when test="criterion.noValue">
                  and ${criterion.condition}
                </when>
                <when test="criterion.singleValue">
                  and ${criterion.condition} #{criterion.value}
                </when>
                <when test="criterion.betweenValue">
                  and ${criterion.condition} #{criterion.value} and #{criterion.secondValue}
                </when>
                <when test="criterion.listValue">
                  and ${criterion.condition}
                  <foreach close=")" collection="criterion.value" item="listItem" open="(" separator=",">
                    #{listItem}
                  </foreach>
                </when>
              </choose>
            </foreach>
          </trim>
        </if>
      </foreach>
    </where>
  </sql>
  <sql id="Update_By_Example_Where_Clause">
    <!--
      WARNING - @mbg.generated
      This element is automatically generated by MyBatis Generator, do not modify.
      This element was generated on Thu May 23 23:24:09 CST 2019.
    -->
    <where>
      <foreach collection="example.oredCriteria" item="criteria" separator="or">
        <if test="criteria.valid">
          <trim prefix="(" prefixOverrides="and" suffix=")">
            <foreach collection="criteria.criteria" item="criterion">
              <choose>
                <when test="criterion.noValue">
                  and ${criterion.condition}
                </when>
                <when test="criterion.singleValue">
                  and ${criterion.condition} #{criterion.value}
                </when>
                <when test="criterion.betweenValue">
                  and ${criterion.condition} #{criterion.value} and #{criterion.secondValue}
                </when>
                <when test="criterion.listValue">
                  and ${criterion.condition}
                  <foreach close=")" collection="criterion.value" item="listItem" open="(" separator=",">
                    #{listItem}
                  </foreach>
                </when>
              </choose>
            </foreach>
          </trim>
        </if>
      </foreach>
    </where>
  </sql>
  <sql id="Base_Column_List">
    <!--
      WARNING - @mbg.generated
      This element is automatically generated by MyBatis Generator, do not modify.
      This element was generated on Thu May 23 23:24:09 CST 2019.
    -->
    ID, TRAINER_NO, PASSWORD, NAME, GENDER, AGE, DRIVING_YEARS, PHONE, ID_NUMBER, LICENSE_TYPE, 
    LICENSE_NO, CAR_ID, SALARY, JOIN_DATE, FLAG, COMMENTS
  </sql>
  <select id="selectByExample" parameterType="com.test.bean.DsmsTrainersExample" resultMap="BaseResultMap">
    <!--
      WARNING - @mbg.generated
      This element is automatically generated by MyBatis Generator, do not modify.
      This element was generated on Thu May 23 23:24:09 CST 2019.
    -->
    select
    <if test="distinct">
      distinct
    </if>
    <include refid="Base_Column_List" />
    from DSMS_TRAINERS
    <if test="_parameter != null">
      <include refid="Example_Where_Clause" />
    </if>
    <if test="orderByClause != null">
      order by ${orderByClause}
    </if>
  </select>
  <select id="selectByPrimaryKey" parameterType="java.lang.Long" resultMap="BaseResultMap">
    <!--
      WARNING - @mbg.generated
      This element is automatically generated by MyBatis Generator, do not modify.
      This element was generated on Thu May 23 23:24:09 CST 2019.
    -->
    select 
    <include refid="Base_Column_List" />
    from DSMS_TRAINERS
    where ID = #{id,jdbcType=DECIMAL}
  </select>
  <delete id="deleteByPrimaryKey" parameterType="java.lang.Long">
    <!--
      WARNING - @mbg.generated
      This element is automatically generated by MyBatis Generator, do not modify.
      This element was generated on Thu May 23 23:24:09 CST 2019.
    -->
    delete from DSMS_TRAINERS
    where ID = #{id,jdbcType=DECIMAL}
  </delete>
  <delete id="deleteByExample" parameterType="com.test.bean.DsmsTrainersExample">
    <!--
      WARNING - @mbg.generated
      This element is automatically generated by MyBatis Generator, do not modify.
      This element was generated on Thu May 23 23:24:09 CST 2019.
    -->
    delete from DSMS_TRAINERS
    <if test="_parameter != null">
      <include refid="Example_Where_Clause" />
    </if>
  </delete>
  <insert id="insert" parameterType="com.test.bean.DsmsTrainers">
    <!--
      WARNING - @mbg.generated
      This element is automatically generated by MyBatis Generator, do not modify.
      This element was generated on Thu May 23 23:24:09 CST 2019.
    -->
    insert into DSMS_TRAINERS (ID, TRAINER_NO, PASSWORD, 
      NAME, GENDER, AGE, DRIVING_YEARS, 
      PHONE, ID_NUMBER, LICENSE_TYPE, 
      LICENSE_NO, CAR_ID, SALARY, 
      JOIN_DATE, FLAG, COMMENTS
      )
    values (#{id,jdbcType=DECIMAL}, #{trainerNo,jdbcType=VARCHAR}, #{password,jdbcType=VARCHAR}, 
      #{name,jdbcType=VARCHAR}, #{gender,jdbcType=CHAR}, #{age,jdbcType=DECIMAL}, #{drivingYears,jdbcType=DECIMAL}, 
      #{phone,jdbcType=DECIMAL}, #{idNumber,jdbcType=VARCHAR}, #{licenseType,jdbcType=VARCHAR}, 
      #{licenseNo,jdbcType=VARCHAR}, #{carId,jdbcType=DECIMAL}, #{salary,jdbcType=DECIMAL}, 
      #{joinDate,jdbcType=DATE}, #{flag,jdbcType=VARCHAR}, #{comments,jdbcType=VARCHAR}
      )
  </insert>
  <insert id="insertSelective" parameterType="com.test.bean.DsmsTrainers">
    <!--
      WARNING - @mbg.generated
      This element is automatically generated by MyBatis Generator, do not modify.
      This element was generated on Thu May 23 23:24:09 CST 2019.
    -->
     <selectKey order="BEFORE" keyProperty="id" resultType="long"> 
        select dsms_trainers_s.nextval from dual 
    </selectKey>  
    insert into DSMS_TRAINERS
    <trim prefix="(" suffix=")" suffixOverrides=",">
        ID,
      <if test="trainerNo != null">
        TRAINER_NO,
      </if>
      <if test="password != null">
        PASSWORD,
      </if>
      <if test="name != null">
        NAME,
      </if>
      <if test="gender != null">
        GENDER,
      </if>
      <if test="age != null">
        AGE,
      </if>
      <if test="drivingYears != null">
        DRIVING_YEARS,
      </if>
      <if test="phone != null">
        PHONE,
      </if>
      <if test="idNumber != null">
        ID_NUMBER,
      </if>
      <if test="licenseType != null">
        LICENSE_TYPE,
      </if>
      <if test="licenseNo != null">
        LICENSE_NO,
      </if>
      <if test="carId != null">
        CAR_ID,
      </if>
      <if test="salary != null">
        SALARY,
      </if>
      <if test="joinDate != null">
        JOIN_DATE,
      </if>
      <if test="flag != null">
        FLAG,
      </if>
      <if test="comments != null">
        COMMENTS,
      </if>
    </trim>
    <trim prefix="values (" suffix=")" suffixOverrides=",">
        #{id,jdbcType=DECIMAL},
      <if test="trainerNo != null">
        #{trainerNo,jdbcType=VARCHAR},
      </if>
      <if test="password != null">
        #{password,jdbcType=VARCHAR},
      </if>
      <if test="name != null">
        #{name,jdbcType=VARCHAR},
      </if>
      <if test="gender != null">
        #{gender,jdbcType=CHAR},
      </if>
      <if test="age != null">
        #{age,jdbcType=DECIMAL},
      </if>
      <if test="drivingYears != null">
        #{drivingYears,jdbcType=DECIMAL},
      </if>
      <if test="phone != null">
        #{phone,jdbcType=DECIMAL},
      </if>
      <if test="idNumber != null">
        #{idNumber,jdbcType=VARCHAR},
      </if>
      <if test="licenseType != null">
        #{licenseType,jdbcType=VARCHAR},
      </if>
      <if test="licenseNo != null">
        #{licenseNo,jdbcType=VARCHAR},
      </if>
      <if test="carId != null">
        #{carId,jdbcType=DECIMAL},
      </if>
      <if test="salary != null">
        #{salary,jdbcType=DECIMAL},
      </if>
      <if test="joinDate != null">
        #{joinDate,jdbcType=DATE},
      </if>
      <if test="flag != null">
        #{flag,jdbcType=VARCHAR},
      </if>
      <if test="comments != null">
        #{comments,jdbcType=VARCHAR},
      </if>
    </trim>
  </insert>
  <select id="countByExample" parameterType="com.test.bean.DsmsTrainersExample" resultType="java.lang.Long">
    <!--
      WARNING - @mbg.generated
      This element is automatically generated by MyBatis Generator, do not modify.
      This element was generated on Thu May 23 23:24:09 CST 2019.
    -->
    select count(*) from DSMS_TRAINERS
    <if test="_parameter != null">
      <include refid="Example_Where_Clause" />
    </if>
  </select>
  <update id="updateByExampleSelective" parameterType="map">
    <!--
      WARNING - @mbg.generated
      This element is automatically generated by MyBatis Generator, do not modify.
      This element was generated on Thu May 23 23:24:09 CST 2019.
    -->
    update DSMS_TRAINERS
    <set>
      <if test="record.id != null">
        ID = #{record.id,jdbcType=DECIMAL},
      </if>
      <if test="record.trainerNo != null">
        TRAINER_NO = #{record.trainerNo,jdbcType=VARCHAR},
      </if>
      <if test="record.password != null">
        PASSWORD = #{record.password,jdbcType=VARCHAR},
      </if>
      <if test="record.name != null">
        NAME = #{record.name,jdbcType=VARCHAR},
      </if>
      <if test="record.gender != null">
        GENDER = #{record.gender,jdbcType=CHAR},
      </if>
      <if test="record.age != null">
        AGE = #{record.age,jdbcType=DECIMAL},
      </if>
      <if test="record.drivingYears != null">
        DRIVING_YEARS = #{record.drivingYears,jdbcType=DECIMAL},
      </if>
      <if test="record.phone != null">
        PHONE = #{record.phone,jdbcType=DECIMAL},
      </if>
      <if test="record.idNumber != null">
        ID_NUMBER = #{record.idNumber,jdbcType=VARCHAR},
      </if>
      <if test="record.licenseType != null">
        LICENSE_TYPE = #{record.licenseType,jdbcType=VARCHAR},
      </if>
      <if test="record.licenseNo != null">
        LICENSE_NO = #{record.licenseNo,jdbcType=VARCHAR},
      </if>
      <if test="record.carId != null">
        CAR_ID = #{record.carId,jdbcType=DECIMAL},
      </if>
      <if test="record.salary != null">
        SALARY = #{record.salary,jdbcType=DECIMAL},
      </if>
      <if test="record.joinDate != null">
        JOIN_DATE = #{record.joinDate,jdbcType=DATE},
      </if>
      <if test="record.flag != null">
        FLAG = #{record.flag,jdbcType=VARCHAR},
      </if>
      <if test="record.comments != null">
        COMMENTS = #{record.comments,jdbcType=VARCHAR},
      </if>
    </set>
    <if test="_parameter != null">
      <include refid="Update_By_Example_Where_Clause" />
    </if>
  </update>
  <update id="updateByExample" parameterType="map">
    <!--
      WARNING - @mbg.generated
      This element is automatically generated by MyBatis Generator, do not modify.
      This element was generated on Thu May 23 23:24:09 CST 2019.
    -->
    update DSMS_TRAINERS
    set ID = #{record.id,jdbcType=DECIMAL},
      TRAINER_NO = #{record.trainerNo,jdbcType=VARCHAR},
      PASSWORD = #{record.password,jdbcType=VARCHAR},
      NAME = #{record.name,jdbcType=VARCHAR},
      GENDER = #{record.gender,jdbcType=CHAR},
      AGE = #{record.age,jdbcType=DECIMAL},
      DRIVING_YEARS = #{record.drivingYears,jdbcType=DECIMAL},
      PHONE = #{record.phone,jdbcType=DECIMAL},
      ID_NUMBER = #{record.idNumber,jdbcType=VARCHAR},
      LICENSE_TYPE = #{record.licenseType,jdbcType=VARCHAR},
      LICENSE_NO = #{record.licenseNo,jdbcType=VARCHAR},
      CAR_ID = #{record.carId,jdbcType=DECIMAL},
      SALARY = #{record.salary,jdbcType=DECIMAL},
      JOIN_DATE = #{record.joinDate,jdbcType=DATE},
      FLAG = #{record.flag,jdbcType=VARCHAR},
      COMMENTS = #{record.comments,jdbcType=VARCHAR}
    <if test="_parameter != null">
      <include refid="Update_By_Example_Where_Clause" />
    </if>
  </update>
  <update id="updateByPrimaryKeySelective" parameterType="com.test.bean.DsmsTrainers">
    <!--
      WARNING - @mbg.generated
      This element is automatically generated by MyBatis Generator, do not modify.
      This element was generated on Thu May 23 23:24:09 CST 2019.
    -->
    update DSMS_TRAINERS
    <set>
      <if test="trainerNo != null">
        TRAINER_NO = #{trainerNo,jdbcType=VARCHAR},
      </if>
      <if test="password != null">
        PASSWORD = #{password,jdbcType=VARCHAR},
      </if>
      <if test="name != null">
        NAME = #{name,jdbcType=VARCHAR},
      </if>
      <if test="gender != null">
        GENDER = #{gender,jdbcType=CHAR},
      </if>
      <if test="age != null">
        AGE = #{age,jdbcType=DECIMAL},
      </if>
      <if test="drivingYears != null">
        DRIVING_YEARS = #{drivingYears,jdbcType=DECIMAL},
      </if>
      <if test="phone != null">
        PHONE = #{phone,jdbcType=DECIMAL},
      </if>
      <if test="idNumber != null">
        ID_NUMBER = #{idNumber,jdbcType=VARCHAR},
      </if>
      <if test="licenseType != null">
        LICENSE_TYPE = #{licenseType,jdbcType=VARCHAR},
      </if>
      <if test="licenseNo != null">
        LICENSE_NO = #{licenseNo,jdbcType=VARCHAR},
      </if>
        CAR_ID = #{carId,jdbcType=DECIMAL},
      <if test="salary != null">
        SALARY = #{salary,jdbcType=DECIMAL},
      </if>
      <if test="joinDate != null">
        JOIN_DATE = #{joinDate,jdbcType=DATE},
      </if>
      <if test="flag != null">
        FLAG = #{flag,jdbcType=VARCHAR},
      </if>
      <if test="comments != null">
        COMMENTS = #{comments,jdbcType=VARCHAR},
      </if>
    </set>
    where ID = #{id,jdbcType=DECIMAL}
  </update>
  <update id="updateByPrimaryKey" parameterType="com.test.bean.DsmsTrainers">
    <!--
      WARNING - @mbg.generated
      This element is automatically generated by MyBatis Generator, do not modify.
      This element was generated on Thu May 23 23:24:09 CST 2019.
    -->
    update DSMS_TRAINERS
    set TRAINER_NO = #{trainerNo,jdbcType=VARCHAR},
      PASSWORD = #{password,jdbcType=VARCHAR},
      NAME = #{name,jdbcType=VARCHAR},
      GENDER = #{gender,jdbcType=CHAR},
      AGE = #{age,jdbcType=DECIMAL},
      DRIVING_YEARS = #{drivingYears,jdbcType=DECIMAL},
      PHONE = #{phone,jdbcType=DECIMAL},
      ID_NUMBER = #{idNumber,jdbcType=VARCHAR},
      LICENSE_TYPE = #{licenseType,jdbcType=VARCHAR},
      LICENSE_NO = #{licenseNo,jdbcType=VARCHAR},
      CAR_ID = #{carId,jdbcType=DECIMAL},
      SALARY = #{salary,jdbcType=DECIMAL},
      JOIN_DATE = #{joinDate,jdbcType=DATE},
      FLAG = #{flag,jdbcType=VARCHAR},
      COMMENTS = #{comments,jdbcType=VARCHAR}
    where ID = #{id,jdbcType=DECIMAL}
  </update>
</mapper>